inpe_auth/__init__.py
inpe_auth/version.py
inpe_auth-0.0.0.dist-info/METADATA
inpe_auth-0.0.0.dist-info/WHEEL
inpe_auth-0.0.0.dist-info/top_level.txt
inpe_auth-0.0.0.dist-info/RECORD
